clockangle/__init__.py
clockangle/angle_calculator.py
clockangle-1.0.0.dist-info/LICENSE
clockangle-1.0.0.dist-info/METADATA
clockangle-1.0.0.dist-info/WHEEL
clockangle-1.0.0.dist-info/top_level.txt
clockangle-1.0.0.dist-info/RECORD
